rdcompiler/__about__.py
rdcompiler/__init__.py
rdcompiler/__main__.py
rdcompiler/pipelines.py
rdcompiler/utils.py
rdcompiler-0.2.1.dist-info/METADATA
rdcompiler-0.2.1.dist-info/WHEEL
rdcompiler-0.2.1.dist-info/licenses/LICENSE
rdcompiler-0.2.1.dist-info/RECORD
