Metadata-Version: 2.4
Name: rdcompiler
Version: 0.2.1
Summary: A library to compile Rhythm Doctor custom levels.
Project-URL: Documentation, https://github.com/RDCN-Community-Developers/rd-compiler#readme
Project-URL: Issues, https://github.com/RDCN-Community-Developers/rd-compiler/issues
Project-URL: Source, https://github.com/RDCN-Community-Developers/rd-compiler
Author-email: NoMathExpectation <85624722+NoMathExpectation@users.noreply.github.com>
License-File: LICENSE
Classifier: Development Status :: 4 - Beta
Classifier: License :: OSI Approved :: GNU General Public License v3 or later (GPLv3+)
Classifier: Programming Language :: Python
Classifier: Programming Language :: Python :: 3.8
Classifier: Programming Language :: Python :: 3.9
Classifier: Programming Language :: Python :: 3.10
Classifier: Programming Language :: Python :: 3.11
Classifier: Programming Language :: Python :: 3.12
Classifier: Programming Language :: Python :: Implementation :: CPython
Classifier: Programming Language :: Python :: Implementation :: PyPy
Classifier: Topic :: File Formats :: JSON
Classifier: Topic :: Games/Entertainment
Requires-Python: >=3.8
Requires-Dist: json5
